tapper/__init__.py
tapper/cli.py
tapper/exceptions.py
tapper/gateway.py
tapper/load_balancer.py
tapper/models.py
tapper/service.py
tapper/registry/__init__.py
tapper/registry/client.py
tapper/registry/server.py
tapper/registry/backends/__init__.py
tapper/registry/backends/base.py
tapper/registry/backends/memory.py
tapper/registry/backends/redis.py
tyler_ag_tapper-0.1.0.dist-info/METADATA
tyler_ag_tapper-0.1.0.dist-info/WHEEL
tyler_ag_tapper-0.1.0.dist-info/entry_points.txt
tyler_ag_tapper-0.1.0.dist-info/RECORD
