Metadata-Version: 2.4
Name: tyler-ag-tapper
Version: 0.1.0
Summary: A Python microservices framework for FastAPI with service discovery and API gateway routing
Project-URL: Homepage, https://github.com/tapper/tapper
Project-URL: Documentation, https://tapper.readthedocs.io
Author: Tapper Team
License-Expression: MIT
Classifier: Development Status :: 3 - Alpha
Classifier: Framework :: FastAPI
Classifier: Intended Audience :: Developers
Classifier: License :: OSI Approved :: MIT License
Classifier: Programming Language :: Python :: 3
Classifier: Programming Language :: Python :: 3.11
Classifier: Programming Language :: Python :: 3.12
Classifier: Topic :: Internet :: WWW/HTTP
Classifier: Topic :: Software Development :: Libraries :: Application Frameworks
Requires-Python: >=3.11
Requires-Dist: click>=8.0.0
Requires-Dist: fastapi>=0.100.0
Requires-Dist: httpx>=0.25.0
Requires-Dist: pydantic>=2.0.0
Requires-Dist: uvicorn>=0.23.0
Provides-Extra: dev
Requires-Dist: pytest-asyncio>=0.21.0; extra == 'dev'
Requires-Dist: pytest-cov>=4.0.0; extra == 'dev'
Requires-Dist: pytest>=7.0.0; extra == 'dev'
Provides-Extra: redis
Requires-Dist: redis>=5.0.0; extra == 'redis'
